zcryptpy/__init__.py
zcryptpy/main.py
zcryptpy-1.0.1.dist-info/LICENSE
zcryptpy-1.0.1.dist-info/METADATA
zcryptpy-1.0.1.dist-info/WHEEL
zcryptpy-1.0.1.dist-info/top_level.txt
zcryptpy-1.0.1.dist-info/RECORD
