Metadata-Version: 2.1
Name: zcryptpy
Version: 1.0.1
Summary: zCrypt - Simple encryption algorithm
Author-email: Zer0here <lopadotemakho.pterygon@protonmail.com>
Project-URL: Homepage, https://github.com/RefriZaddo/zCrypt.py
Project-URL: Issues, https://github.com/RefriZaddo/zCrypt.py/issues
Classifier: Programming Language :: Python :: 3
Classifier: License :: OSI Approved :: MIT License
Classifier: Operating System :: OS Independent
Requires-Python: >=3.8
License-File: LICENSE
